colormaps/__init__.py
colormaps/_version.py
colormaps/cmaps.py
colormaps/colormap.py
colormaps/utils.py
colormaps/colormaps/carbonplan/bluegrey_dark.rgb
colormaps/colormaps/carbonplan/bluegrey_light.rgb
colormaps/colormaps/carbonplan/blues_dark.rgb
colormaps/colormaps/carbonplan/blues_light.rgb
colormaps/colormaps/carbonplan/cool_dark.rgb
colormaps/colormaps/carbonplan/cool_light.rgb
colormaps/colormaps/carbonplan/earth_dark.rgb
colormaps/colormaps/carbonplan/earth_light.rgb
colormaps/colormaps/carbonplan/fire_dark.rgb
colormaps/colormaps/carbonplan/fire_light.rgb
colormaps/colormaps/carbonplan/greengrey_dark.rgb
colormaps/colormaps/carbonplan/greengrey_light.rgb
colormaps/colormaps/carbonplan/greens_dark.rgb
colormaps/colormaps/carbonplan/greens_light.rgb
colormaps/colormaps/carbonplan/greys_dark.rgb
colormaps/colormaps/carbonplan/greys_light.rgb
colormaps/colormaps/carbonplan/heart_dark.rgb
colormaps/colormaps/carbonplan/heart_light.rgb
colormaps/colormaps/carbonplan/orangeblue_dark.rgb
colormaps/colormaps/carbonplan/orangeblue_light.rgb
colormaps/colormaps/carbonplan/orangegrey_dark.rgb
colormaps/colormaps/carbonplan/orangegrey_light.rgb
colormaps/colormaps/carbonplan/oranges_dark.rgb
colormaps/colormaps/carbonplan/oranges_light.rgb
colormaps/colormaps/carbonplan/pinkgreen_dark.rgb
colormaps/colormaps/carbonplan/pinkgreen_light.rgb
colormaps/colormaps/carbonplan/pinkgrey_dark.rgb
colormaps/colormaps/carbonplan/pinkgrey_light.rgb
colormaps/colormaps/carbonplan/pinks_dark.rgb
colormaps/colormaps/carbonplan/pinks_light.rgb
colormaps/colormaps/carbonplan/purplegrey_dark.rgb
colormaps/colormaps/carbonplan/purplegrey_light.rgb
colormaps/colormaps/carbonplan/purples_dark.rgb
colormaps/colormaps/carbonplan/purples_light.rgb
colormaps/colormaps/carbonplan/rainbow_dark.rgb
colormaps/colormaps/carbonplan/rainbow_light.rgb
colormaps/colormaps/carbonplan/redgrey_dark.rgb
colormaps/colormaps/carbonplan/redgrey_light.rgb
colormaps/colormaps/carbonplan/reds_dark.rgb
colormaps-0.4.1.dist-info/LICENSE
colormaps-0.4.1.dist-info/METADATA
colormaps-0.4.1.dist-info/WHEEL
colormaps-0.4.1.dist-info/top_level.txt
colormaps-0.4.1.dist-info/RECORD
