Metadata-Version: 2.1
Name: colormaps
Version: 0.4.1
Summary: Collection of colormaps or color palettes for Python
Home-page: https://pratiman-91.github.io/colormaps/
Author: Pratiman Patel
Author-email: Pratiman Patel <pratiman_patel@hotmail.com>
License: LICENSE
Project-URL: Homepage, https://pratiman-91.github.io/colormaps/
Project-URL: Bug Tracker, https://github.com/pratiman-91/colormaps/issues
Classifier: Programming Language :: Python :: 3
Classifier: License :: OSI Approved :: MIT License
Classifier: Operating System :: OS Independent
Requires-Python: >=3.7
License-File: LICENSE
Requires-Dist: matplotlib
Requires-Dist: numpy
